tlp/__init__.py
tlp/core.py
tlp/instance.py
tlp/task.py
tlp/tlpc.py
tlp/tlpv.py
tlp/util.py
tlp/assets/cpp/tlp.h
tlp/assets/cpp/tlp/mmap.h
tlp/assets/cpp/tlp/stream.h
tlp/assets/verilog/async_mmap.v
tlp/assets/verilog/detect_burst.v
tlp/assets/verilog/generate_last.v
tlp/assets/verilog/relay_station.v
tlp/verilog/__init__.py
tlp/verilog/ast.py
tlp/verilog/util.py
tlp/verilog/xilinx.py
tlpc-0.0.20200716.1.dist-info/METADATA
tlpc-0.0.20200716.1.dist-info/WHEEL
tlpc-0.0.20200716.1.dist-info/entry_points.txt
tlpc-0.0.20200716.1.dist-info/top_level.txt
tlpc-0.0.20200716.1.dist-info/RECORD
