Metadata-Version: 2.1
Name: tlpc
Version: 0.0.20200716.1
Summary: High-level synthesis task-level parallelization
Home-page: https://github.com/Blaok/tlp
Author: Blaok Chi
License: UNKNOWN
Platform: UNKNOWN
Classifier: Development Status :: 2 - Pre-Alpha
Classifier: Intended Audience :: Developers
Classifier: Intended Audience :: Science/Research
Classifier: License :: OSI Approved :: MIT License
Classifier: Programming Language :: Python :: 3 :: Only
Classifier: Programming Language :: Python :: 3
Classifier: Programming Language :: Python :: 3.6
Classifier: Programming Language :: Python :: 3.7
Classifier: Programming Language :: Python :: 3.8
Classifier: Programming Language :: Python :: 3.9
Classifier: Topic :: System :: Hardware
Requires-Python: >=3.6
Requires-Dist: haoda (>=0.0.20200507.dev1)
Requires-Dist: pyverilog (>=1.2.0)
